[{"repo": "jina-ai/jina", "name": "jina-ai-jina", "host": "https://jina-ai-jina.docsqa.jina.ai", "uptime": 1, "status": "AVAILABLE", "ctime": "2022-07-21T07:00:17.802578", "last_utime": "2022-07-21T07:00:51.172296", "last_dtime": null, "history": [{"ctime": "2022-07-21T07:00:51.172304", "status": "AVAILABLE"}]}, {"repo": "jina-ai/finetuner", "name": "jina-ai-finetuner", "host": "https://jina-ai-finetuner.docsqa.jina.ai", "uptime": 1, "status": "AVAILABLE", "ctime": "2022-07-21T07:00:17.802578", "last_utime": "2022-07-21T07:01:12.491094", "last_dtime": null, "history": [{"ctime": "2022-07-21T07:01:12.491101", "status": "AVAILABLE"}]}, {"repo": "tiangolo/fastapi", "name": "tiangolo-fastapi", "host": "https://tiangolo-fastapi.docsqa.jina.ai", "uptime": 1, "status": "AVAILABLE", "ctime": "2022-07-21T07:00:17.802578", "last_utime": "2022-07-21T07:01:46.660321", "last_dtime": null, "history": [{"ctime": "2022-07-21T07:01:46.660324", "status": "AVAILABLE"}]}, {"repo": "tiangolo/typer", "name": "tiangolo-typer", "host": "https://tiangolo-typer.docsqa.jina.ai", "uptime": 1, "status": "AVAILABLE", "ctime": "2022-07-21T07:00:17.802578", "last_utime": "2022-07-21T07:02:02.218692", "last_dtime": null, "history": [{"ctime": "2022-07-21T07:02:02.218699", "status": "AVAILABLE"}]}, {"repo": "tiangolo/sqlmodel", "name": "tiangolo-sqlmodel", "host": "https://tiangolo-sqlmodel.docsqa.jina.ai", "uptime": 1, "status": "AVAILABLE", "ctime": "2022-07-21T07:00:17.802578", "last_utime": "2022-07-21T07:02:17.571442", "last_dtime": null, "history": [{"ctime": "2022-07-21T07:02:17.571449", "status": "AVAILABLE"}]}, {"repo": "jina-ai/docarray", "name": "jina-ai-docarray", "host": "https://jina-ai-docarray.docsqa.jina.ai", "uptime": 1, "status": "AVAILABLE", "ctime": "2022-07-21T07:00:17.802578", "last_utime": "2022-07-21T07:02:19.265435", "last_dtime": null, "history": [{"ctime": "2022-07-21T07:02:19.265437", "status": "AVAILABLE"}]}, {"repo": "coqui-ai/TTS", "name": "coqui-ai-tts", "host": "https://coqui-ai-tts.docsqa.jina.ai", "uptime": 1, "status": "AVAILABLE", "ctime": "2022-07-21T07:00:17.802578", "last_utime": "2022-07-21T07:02:32.016702", "last_dtime": null, "history": [{"ctime": "2022-07-21T07:02:32.016705", "status": "AVAILABLE"}]}, {"repo": "coqui-ai/STT", "name": "coqui-ai-stt", "host": "https://coqui-ai-stt.docsqa.jina.ai", "uptime": 1, "status": "AVAILABLE", "ctime": "2022-07-21T07:00:17.802578", "last_utime": "2022-07-21T07:02:51.831223", "last_dtime": null, "history": [{"ctime": "2022-07-21T07:02:51.831229", "status": "AVAILABLE"}]}, {"repo": "insideout10/wordlift-docs", "name": "insideout10-wordlift-docs", "host": "https://insideout10-wordlift-docs.docsqa.jina.ai", "uptime": 1, "status": "AVAILABLE", "ctime": "2022-07-21T07:00:17.802578", "last_utime": "2022-07-21T07:03:08.624505", "last_dtime": null, "history": [{"ctime": "2022-07-21T07:03:08.624510", "status": "AVAILABLE"}]}, {"repo": "kornia/kornia", "name": "kornia-kornia", "host": "https://kornia-kornia.docsqa.jina.ai", "uptime": 1, "status": "AVAILABLE", "ctime": "2022-07-21T07:00:17.802578", "last_utime": "2022-07-21T07:03:19.620581", "last_dtime": null, "history": [{"ctime": "2022-07-21T07:03:19.620589", "status": "AVAILABLE"}]}, {"repo": "jina-ai/clip-as-service", "name": "jina-ai-clip-as-service", "host": "https://jina-ai-clip-as-service.docsqa.jina.ai", "uptime": 1, "status": "AVAILABLE", "ctime": "2022-07-21T07:00:17.802578", "last_utime": "2022-07-21T07:03:44.726280", "last_dtime": null, "history": [{"ctime": "2022-07-21T07:03:44.726288", "status": "AVAILABLE"}]}, {"repo": "shazhou2015/clip-as-service", "name": "shazhou2015-clip-as-service", "host": "https://shazhou2015-clip-as-service.docsqa.jina.ai", "uptime": 1, "status": "AVAILABLE", "ctime": "2022-07-21T07:00:17.802578", "last_utime": "2022-07-21T07:04:08.176817", "last_dtime": null, "history": [{"ctime": "2022-07-21T07:04:08.176823", "status": "AVAILABLE"}]}, {"repo": "jina-ai/now", "name": "jina-ai-now", "host": "https://jina-ai-now.docsqa.jina.ai", "uptime": 1, "status": "AVAILABLE", "ctime": "2022-07-21T07:00:17.802578", "last_utime": "2022-07-21T07:04:20.190953", "last_dtime": null, "history": [{"ctime": "2022-07-21T07:04:20.190955", "status": "AVAILABLE"}]}, {"repo": "fogx/jina", "name": "fogx-jina", "host": "https://fogx-jina.docsqa.jina.ai", "uptime": 1, "status": "AVAILABLE", "ctime": "2022-07-21T07:00:17.802578", "last_utime": "2022-07-21T07:04:33.233643", "last_dtime": null, "history": [{"ctime": "2022-07-21T07:04:33.233651", "status": "AVAILABLE"}]}, {"repo": "alt-shreya/jina", "name": "alt-shreya-jina", "host": "https://alt-shreya-jina.docsqa.jina.ai", "uptime": 1, "status": "AVAILABLE", "ctime": "2022-07-21T07:00:17.802578", "last_utime": "2022-07-21T07:04:47.394563", "last_dtime": null, "history": [{"ctime": "2022-07-21T07:04:47.394568", "status": "AVAILABLE"}]}, {"repo": "wj-Mcat/python-wechaty", "name": "wj-mcat-python-wechaty", "host": "https://wj-mcat-python-wechaty.docsqa.jina.ai", "uptime": 1, "status": "AVAILABLE", "ctime": "2022-07-21T07:00:17.802578", "last_utime": "2022-07-21T07:05:07.835215", "last_dtime": null, "history": [{"ctime": "2022-07-21T07:05:07.835217", "status": "AVAILABLE"}]}, {"repo": "kivy/kivy", "name": "kivy-kivy", "host": "https://kivy-kivy.docsqa.jina.ai", "uptime": 1, "status": "AVAILABLE", "ctime": "2022-07-21T07:00:17.802578", "last_utime": "2022-07-21T07:05:09.434562", "last_dtime": null, "history": [{"ctime": "2022-07-21T07:05:09.434564", "status": "AVAILABLE"}]}, {"repo": "fogx/dalle-flow", "name": "fogx-dalle-flow", "host": "https://fogx-dalle-flow.docsqa.jina.ai", "uptime": 1, "status": "AVAILABLE", "ctime": "2022-07-21T07:00:17.802578", "last_utime": "2022-07-21T07:05:24.897808", "last_dtime": null, "history": [{"ctime": "2022-07-21T07:05:24.897813", "status": "AVAILABLE"}]}]